{"wynnpool":{"Crusade Sabatons":{"Main":{"rawHealth":0.8,"walkSpeed":0.125,"healthRegen":0.075}},"Resurgence":{"Combat":{"manaRegen":0.525,"spellDamage":0.175,"healthRegenRaw":0.225,"walkSpeed":0.075},"Utility":{"manaRegen":0.45,"healthRegenRaw":0.4,"walkSpeed":0.075,"spellDamage":0.075}},"Resonance":{"Main":{"elementalSpellDamage":0.75,"manaRegen":0.2,"4thSpellCost":0.05}},"Boreal":{"Main":{"healthRegen":0.55,"healthRegenRaw":0.28,"manaRegen":0.05,"walkSpeed":0.1,"earthDamage":0.01,"thunderDamage":0.01}},"Slayer":{"Main":{"3rdSpellCost":0.5,"healthRegenRaw":0.35,"walkSpeed":0.15}},"Moontower":{"Main":{"walkSpeed":0.98,"waterDefence":0.01,"airDefence":0.01}},"Dawnbreak":{"Spell":{"manaSteal":0.4,"lifeSteal":0.25,"thunderDamage":0.17,"fireDamage":0.17,"rawMainAttackDamage":0.01},"Melee":{"rawMainAttackDamage":0.55,"lifeSteal":0.125,"manaSteal":0.2,"fireDamage":0.025,"exploding":0.09,"thunderDamage":0.01}},"Labyrinth":{"Main":{"fireDamage":0.475,"earthDamage":0.45,"3rdSpellCost":0.05,"slowEnemy":0.025}},"Cataclysm":{"Main":{"rawHealth":0.45,"raw1stSpellCost":0.45,"thunderDamage":0.1}},"Hanafubuki":{"Main":{"elementalDamage":0.75,"3rdSpellCost":0.175,"4thSpellCost":0.025,"jumpHeight":0.05}},"Oblivion":{"Main":{"manaRegen":0.325,"raw2ndSpellCost":0.075,"rawSpellDamage":0.15,"manaSteal":0.45},"Heavy Melee":{"manaSteal":0.39,"raw2ndSpellCost":0.125,"exploding":0.2,"rawSpellDamage":0.01,"manaRegen":0.275}},"Nirvana":{"Main":{"spellDamage":0.475,"rawHealth":0.225,"manaRegen":0.29,"manaSteal":0.01},"Acrobat":{"spellDamage":0.475,"manaRegen":0.15,"rawHealth":0.35,"manaSteal":0.025}},"Grimtrap":{"Shade":{"poison":0.1,"raw2ndSpellCost":0.15,"raw4thSpellCost":0.65,"manaSteal":0.05,"lifeSteal":0.05},"Cherry Bombs":{"raw4thSpellCost":0.85,"raw2ndSpellCost":0.1,"poison":0.05}},"Weathered":{"Spellsteal":{"manaSteal":0.45,"walkSpeed":0.35,"airDamage":0.2},"Spell":{"walkSpeed":0.65,"airDamage":0.35}},"Nullification":{"Main":{"elementalDefence":0.6,"manaSteal":0.2,"lifeSteal":0.15,"reflection":0.05}},"Archangel":{"Offhand":{"walkSpeed":0.375,"healthRegenRaw":0.275,"healthRegen":0.225,"mainAttackRange":0.05,"rawHealth":0.075}},"Absolution":{"Main":{"healingEfficiency":0.55,"rawHealth":0.2,"manaRegen":0.15,"fireDamage":0.05,"raw1stSpellCost":0.05},"War":{"rawHealth":0.225,"manaRegen":0.05,"healingEfficiency":0.725}},"Sunstar":{"Main":{"rawMainAttackDamage":0.65,"lifeSteal":0.175,"thunderDamage":0.175}},"Hadal":{"Acolyte":{"spellDamage":0.7,"manaRegen":0.2,"3rdSpellCost":0.045,"4thSpellCost":0.045,"rawMaxMana":0.01}},"Aftershock":{"Main":{"earthDamage":0.4,"rawHealth":0.35,"4thSpellCost":0.24,"spellDamage":0.01}},"Discoverer":{"Main":{"xpBonus":0.005,"lootBonus":0.995}},"Trance":{"Main":{"manaSteal":0.65,"rawAttackSpeed":0.2,"walkSpeed":0.1,"lifeSteal":0.05}},"Quetzalcoatl":{"Main":{"rawSpellDamage":0.55,"walkSpeed":0.3,"lifeSteal":0.15}},"Fatal":{"Arcanist":{"spellDamage":0.5,"walkSpeed":0.325,"2ndSpellCost":0.175},"Lightbender":{"spellDamage":0.35,"manaSteal":0.075,"1stSpellCost":0.25,"walkSpeed":0.2,"2ndSpellCost":0.125}},"Singularity":{"Spell":{"rawSpellDamage":0.425,"spellDamage":0.1,"walkSpeed":0.325,"healthRegenRaw":0.15},"Hybrid":{"rawSpellDamage":0.275,"walkSpeed":0.225,"rawMainAttackDamage":0.25,"mainAttackDamage":0.04,"spellDamage":0.06,"healthRegenRaw":0.15}},"Warp":{"Arcanist":{"healthRegen":0.02,"healthRegenRaw":0.375,"manaRegen":0.225,"walkSpeed":0.3,"airDamage":0.08},"Lightbender":{"walkSpeed":0.25,"manaRegen":0.275,"healingEfficiency":0.275,"airDamage":0,"healthRegen":-0.125,"healthRegenRaw":-0.075},"Lootrun":{"walkSpeed":0.2,"manaRegen":0.275,"healingEfficiency":0.075,"healthRegenRaw":0.325,"raw2ndSpellCost":0.025,"healthRegen":0.075,"airDamage":0.025}},"Immolation":{"Main":{"healthRegen":0.01,"3rdSpellCost":0.33,"fireDamage":0.33,"airDamage":0.33},"HPR% Cancel":{"3rdSpellCost":0.25,"healthRegen":0.25,"fireDamage":0.25,"airDamage":0.25}},"Lament":{"Main":{"waterDamage":0.45,"manaSteal":0.325,"1stSpellCost":0.075,"healingEfficiency":0.15},"Offhand":{"waterDamage":0.525,"1stSpellCost":0.225,"healingEfficiency":0.25}},"Toxoplasmosis":{"Mob Grinding":{"lootBonus":0.49,"poison":0.5,"walkSpeed":0.01},"Main":{"poison":0.8,"walkSpeed":0.1,"manaSteal":0.05,"lifeSteal":0.05}},"Pure":{"Main":{"spellDamage":0.85,"manaSteal":0.15},"Leveling":{"xpBonus":0.25,"manaSteal":0.1,"spellDamage":0.65}},"Epoch":{"Main":{"lifeSteal":0.35,"rawMainAttackDamage":0.28,"walkSpeed":0.25,"raw4thSpellCost":0.1,"manaSteal":0.01,"sprint":0.01}},"Stratiformis":{"Main":{"walkSpeed":0.75,"spellDamage":0.1,"rawHealth":0.15}},"Divzer":{"Main":{"manaSteal":0.75,"lifeSteal":0.15,"rawSpellDamage":0.1}},"Spring":{"Main":{"manaRegen":0.45,"waterDamage":0.3,"slowEnemy":0.025,"thunderDamage":0.075,"weakenEnemy":0.15}},"Collapse":{"Spell":{"elementalDefence":0.7,"manaSteal":0.275,"mainAttackDamage":0.025},"Melee":{"mainAttackDamage":0.75,"elementalDefence":0.15,"manaSteal":0.1}},"Az":{"Leveling":{"xpBonus":0.4,"1stSpellCost":0.3,"fireDamage":0.15,"waterDamage":0.15},"Combat":{"1stSpellCost":0.35,"waterDamage":0.35,"fireDamage":0.3}},"Freedom":{"Main":{"rawSpellDamage":0.15,"rawHealth":0.2,"walkSpeed":0.35,"manaRegen":0.3},"\ud835\udcd0\ud835\udcdc\ud835\udcd4\ud835\udce1\ud835\udcd8\ud835\udcd2\ud835\udcd0 \ud83e\udd85":{"rawMainAttackDamage":0.69,"rawSpellDamage":0.69,"rawHealth":0.69,"manaRegen":0.69,"walkSpeed":0.69}},"Alkatraz":{"Spell":{"earthDamage":0.99,"exploding":0.01},"Melee":{"earthDamage":0.325,"mainAttackDamage":0.325,"exploding":0.35}},"Thrundacrack":{"Main":{"raw3rdSpellCost":0.55,"thunderDamage":0.4,"waterDamage":0.025,"walkSpeed":0.025}},"Guardian":{"War":{"rawHealth":0.99,"manaRegen":0.009,"healthRegenRaw":0.001},"Combat":{"healthRegenRaw":0.1,"manaRegen":0.05,"rawHealth":0.85},"Big Mac":{"rawHealth":-0.3,"manaRegen":0.05,"healthRegenRaw":0.65}},"Hero":{"Main":{"walkSpeed":0.95,"mainAttackDamage":0.01,"healthRegen":0.04}},"Grandmother":{"HPR% Cancel":{"spellDamage":0.675,"healthRegen":0.25,"walkSpeed":0.075}},"Ignis":{"Offhand":{"healthRegen":0.425,"healthRegenRaw":0.5,"rawHealth":0.025,"4thSpellCost":0.05},"Mainhand":{"healthRegen":0.3,"healthRegenRaw":0.4,"rawHealth":0.2,"4thSpellCost":0.1}},"Stardew":{"Obli":{"manaSteal":0.425,"manaRegen":0.17,"thunderDamage":0.11,"waterDamage":0.105,"rawSpellDamage":0.19},"Water spell":{"rawSpellDamage":0.475,"manaRegen":0.15,"waterDamage":0.35,"thunderDamage":0.025},"Water spellsteal":{"rawSpellDamage":0.325,"waterDamage":0.25,"manaSteal":0.275,"manaRegen":0.14,"thunderDamage":0.01},"Tcrack":{"rawSpellDamage":0.6,"thunderDamage":0.38,"waterDamage":0.02}},"Convergence":{"Main":{"3rdSpellCost":0.7,"earthDamage":0.125,"thunderDamage":0.125,"healthRegen":0.05}},"Bloodbath":{"High HP":{"raw1stSpellCost":0.5,"rawHealth":0.3,"walkSpeed":0.2},"Low HP":{"rawHealth":-0.15,"raw1stSpellCost":0.6,"walkSpeed":0.25}},"Monster":{"Main":{"rawHealth":0.65,"manaSteal":0.15,"fireDamage":0.175,"raw1stSpellCost":0.025,"lifeSteal":0},"War":{"rawHealth":0.8,"fireDamage":0.075,"manaSteal":0.075,"raw1stSpellCost":0.05}},"Fantasia":{"Main":{"spellDamage":0.3,"manaRegen":0.25,"3rdSpellCost":0.2,"4thSpellCost":0.15,"1stSpellCost":0.075,"2ndSpellCost":0.025}},"Warchief":{"Epoch":{"mainAttackDamage":0.46,"thunderDamage":0.2,"walkSpeed":0.135,"rawMainAttackDamage":0.18,"exploding":0.025},"Alkatraz":{"walkSpeed":0.1,"earthDamage":0.21,"rawMainAttackDamage":0.17,"mainAttackDamage":0.37,"exploding":0.15},"Spell":{"earthDamage":0.35,"thunderDamage":0.5,"walkSpeed":0.15},"Sunstar":{"thunderDamage":0.25,"mainAttackDamage":0.375,"rawMainAttackDamage":0.19,"walkSpeed":0.05,"exploding":0.135}},"Olympic":{"Main":{"jumpHeight":0.3,"walkSpeed":0.3,"airDamage":0.175,"raw1stSpellCost":0.2,"raw2ndSpellCost":0.025}},"Revenant":{"Olympic":{"rawHealth":0.15,"4thSpellCost":0.075,"manaSteal":0.025,"airDamage":0.425,"walkSpeed":0.325},"Hero":{"4thSpellCost":0.4,"walkSpeed":0.325,"airDamage":0.225,"earthDamage":0.01,"rawHealth":0.04},"Air Quetz":{"walkSpeed":0.275,"rawHealth":0.065,"4thSpellCost":0.2,"airDamage":0.25,"earthDamage":0.175,"manaSteal":0.035},"General":{"earthDamage":0.2,"airDamage":0.275,"rawHealth":0.075,"4thSpellCost":0.175,"walkSpeed":0.25,"manaSteal":0.025}},"Gaia":{"Spell":{"raw4thSpellCost":0.9,"poison":0.1},"Offhand":{"raw4thSpellCost":1}},"Inferno":{"Main":{"rawMainAttackDamage":0.6,"walkSpeed":0.225,"fireDamage":0.05,"raw1stSpellCost":0.025,"rawHealth":0.1}},"Apocalypse":{"Main":{"lifeSteal":0.8,"healthRegen":0.13,"fireDefence":0.01,"waterDamage":0.01,"exploding":0.05}},"Galleon":{"Resonance":{"manaSteal":0.225,"waterDamage":0.4,"earthDamage":0.325,"rawMaxMana":0.05}},"Idol":{"Raid":{"manaRegen":0.14,"raw2ndSpellCost":0.01,"rawSpellDamage":0.85},"Lootrun":{"manaRegen":0.15,"rawSpellDamage":0.35,"raw2ndSpellCost":0.5}}},"nori":{"Apocalypse":{"Main":{"lifeSteal":0.75,"exploding":0.105,"healthRegen":0.1,"waterDamage":0.02,"fireDefence":0.015,"waterDefence":0.01}},"Hero":{"Main":{"walkSpeed":0.95,"healthRegen":0.04,"mainAttackDamage":0.01}},"Guardian":{"Main":{"rawHealth":0.97,"manaRegen":0.02,"healthRegenRaw":0.01},"Support":{"rawHealth":0.55,"healthRegenRaw":0.4,"manaRegen":0.05},"Burger":{"healthRegenRaw":0.7,"rawHealth":-0.25,"manaRegen":0.05}},"Alkatraz":{"Main":{"earthDamage":0.45,"mainAttackDamage":0.45,"exploding":0.1},"Spell":{"earthDamage":0.98,"mainAttackDamage":0.01,"exploding":0.01}},"Idol":{"Main":{"raw2ndSpellCost":0.49,"rawSpellDamage":0.4,"manaRegen":0.1,"reflection":0.01},"Utility":{"raw2ndSpellCost":0.65,"manaRegen":0.3,"reflection":0.04,"rawSpellDamage":0.01}},"Thrundacrack":{"Main":{"raw3rdSpellCost":0.5,"thunderDamage":0.35,"walkSpeed":0.14,"healthRegen":0.01},"Water":{"raw3rdSpellCost":0.35,"thunderDamage":0.35,"waterDamage":0.225,"walkSpeed":0.065,"healthRegen":0.01}},"Collapse":{"Main":{"manaSteal":0.79,"elementalDefence":0.2,"mainAttackDamage":0.01},"Melee":{"mainAttackDamage":0.85,"manaSteal":0.14,"elementalDefence":0.01}},"Convergence":{"Main":{"3rdSpellCost":0.6,"thunderDamage":0.39,"healthRegen":0.01},"Earth":{"3rdSpellCost":0.6,"earthDamage":0.39,"healthRegen":0.01},"Hpr":{"3rdSpellCost":0.6,"healthRegen":0.25,"thunderDamage":0.08,"earthDamage":0.07}},"Az":{"Main":{"xpBonus":0.3,"1stSpellCost":0.3,"waterDamage":0.2,"fireDamage":0.2},"Elemental":{"1stSpellCost":0.4,"waterDamage":0.3,"fireDamage":0.3}},"Freedom":{"Main":{"rawHealth":0.3,"walkSpeed":0.25,"rawSpellDamage":0.25,"manaRegen":0.2}},"Grandmother":{"Main":{"spellDamage":0.6,"healthRegen":0.35,"walkSpeed":0.05},"HprRaw":{"healthRegenRaw":0.55,"spellDamage":0.35,"healthRegen":0.05,"walkSpeed":0.05}},"Ignis":{"Main":{"healthRegenRaw":0.4,"healthRegen":0.25,"rawHealth":0.25,"4thSpellCost":0.1},"Offhand":{"healthRegenRaw":0.5,"healthRegen":0.45,"rawHealth":0.025,"4thSpellCost":0.025}},"Divzer":{"Main":{"manaSteal":0.85,"lifeSteal":0.1,"rawSpellDamage":0.05}},"Spring":{"Main":{"manaRegen":0.5,"waterDamage":0.4,"weakenEnemy":0.05,"thunderDamage":0.05},"Debuff":{"manaRegen":0.35,"weakenEnemy":0.25,"slowEnemy":0.19,"waterDamage":0.19,"thunderDamage":0.02}},"Stratiformis":{"Main":{"walkSpeed":0.8,"rawHealth":0.16,"spellDamage":0.04}},"Epoch":{"Main":{"rawMainAttackDamage":0.4,"lifeSteal":0.3,"walkSpeed":0.15,"raw4thSpellCost":0.1,"spellDamage":0.05},"Hmelee":{"rawMainAttackDamage":0.4,"lifeSteal":0.35,"raw1stSpellCost":0.1,"raw4thSpellCost":0.05,"spellDamage":0.05,"manaSteal":0.05}},"Pure":{"Main":{"spellDamage":0.55,"xpBonus":0.3,"manaSteal":0.15},"Raid":{"spellDamage":0.9,"manaSteal":0.1}},"Lament":{"Main":{"waterDamage":0.5,"manaSteal":0.225,"healingEfficiency":0.175,"1stSpellCost":0.1},"War":{"waterDamage":0.375,"healingEfficiency":0.3,"manaSteal":0.225,"1stSpellCost":0.1},"Offhand":{"waterDamage":0.55,"healingEfficiency":0.25,"1stSpellCost":0.2}},"Gaia":{"Main":{"rawMainAttackDamage":0.5,"mainAttackDamage":0.3,"poison":0.2},"Spell":{"raw4thSpellCost":0.8,"poison":0.165,"rawMainAttackDamage":0.025,"mainAttackDamage":0.01}},"Monster":{"Main":{"rawHealth":0.5,"fireDamage":0.25,"manaSteal":0.225,"raw1stSpellCost":0.025},"War":{"rawHealth":0.375,"manaSteal":0.275,"fireDamage":0.175,"lifeSteal":0.125,"raw1stSpellCost":0.05}},"Singularity":{"Main":{"rawSpellDamage":0.35,"walkSpeed":0.25,"rawMainAttackDamage":0.15,"healthRegenRaw":0.1,"spellDamage":0.1,"mainAttackDamage":0.05}},"Fatal":{"Main":{"spellDamage":0.6,"walkSpeed":0.2,"2ndSpellCost":0.15,"manaSteal":0.05},"Riftwalker":{"spellDamage":0.4,"1stSpellCost":0.25,"2ndSpellCost":0.15,"manaSteal":0.1,"walkSpeed":0.1}},"Warp":{"Main":{"healthRegenRaw":0.45,"walkSpeed":0.25,"manaRegen":0.2,"airDamage":0.075,"healthRegen":0.025},"Lightbender":{"manaRegen":0.3,"walkSpeed":0.3,"healingEfficiency":0.25,"healthRegenRaw":0.075,"airDamage":0.05,"healthRegen":0.025},"Lootrun":{"healthRegenRaw":0.3,"walkSpeed":0.225,"manaRegen":0.2,"raw2ndSpellCost":0.1,"healthRegen":0.075,"healingEfficiency":0.05,"airDamage":0.05}},"Quetzalcoatl":{"Main":{"rawSpellDamage":0.55,"walkSpeed":0.3,"lifeSteal":0.15}},"Aftershock":{"Main":{"rawHealth":0.5,"earthDamage":0.4,"4thSpellCost":0.075,"spellDamage":0.025}},"Olympic":{"Main":{"jumpHeight":0.35,"walkSpeed":0.3,"airDamage":0.175,"raw1stSpellCost":0.15,"raw2ndSpellCost":0.025}},"Hadal":{"Main":{"spellDamage":0.625,"manaRegen":0.2,"3rdSpellCost":0.1,"4thSpellCost":0.065,"rawMaxMana":0.01}},"Sunstar":{"Main":{"rawMainAttackDamage":0.6,"thunderDamage":0.25,"lifeSteal":0.15}},"Toxoplasmosis":{"Main":{"poison":0.6,"lootBonus":0.39,"walkSpeed":0.01},"Combat":{"poison":0.89,"walkSpeed":0.075,"manaSteal":0.025,"lifeSteal":0.01}},"Fantasia":{"Main":{"3rdSpellCost":0.275,"spellDamage":0.225,"manaRegen":0.2,"4thSpellCost":0.15,"1stSpellCost":0.08,"manaSteal":0.06,"2ndSpellCost":0.01}},"Absolution":{"Main":{"healingEfficiency":0.5,"rawHealth":0.225,"manaRegen":0.175,"raw1stSpellCost":0.09,"fireDamage":0.01}},"Immolation":{"Main":{"fireDamage":0.33,"airDamage":0.33,"3rdSpellCost":0.33,"healthRegen":0.01},"Hpr%":{"healthRegen":0.265,"fireDamage":0.25,"airDamage":0.25,"3rdSpellCost":0.235}},"Archangel":{"Main":{"walkSpeed":0.325,"rawHealth":0.225,"healthRegen":0.175,"healthRegenRaw":0.175,"mainAttackRange":0.1},"Utility":{"walkSpeed":0.7,"rawHealth":0.1,"healthRegen":0.1,"healthRegenRaw":0.1},"Tank":{"healthRegenRaw":0.325,"healthRegen":0.325,"rawHealth":0.25,"walkSpeed":0.1}},"Nullification":{"Main":{"elementalDefence":0.67,"lifeSteal":0.14,"manaSteal":0.14,"reflection":0.05}},"Cataclysm":{"Main":{"rawHealth":0.5,"raw1stSpellCost":0.3,"thunderDamage":0.19,"stealing":0.01}},"Grimtrap":{"Main":{"raw4thSpellCost":0.7,"raw2ndSpellCost":0.15,"poison":0.1,"manaSteal":0.025,"lifeSteal":0.025}},"Weathered":{"Main":{"airDamage":0.45,"walkSpeed":0.4,"manaSteal":0.15}},"Inferno":{"Main":{"rawMainAttackDamage":0.45,"walkSpeed":0.2,"fireDamage":0.15,"rawHealth":0.15,"raw1stSpellCost":0.05}},"Nirvana":{"Main":{"spellDamage":0.4,"manaRegen":0.3,"manaSteal":0.15,"rawHealth":0.15}},"Oblivion":{"Main":{"manaSteal":0.45,"manaRegen":0.3,"rawSpellDamage":0.175,"raw2ndSpellCost":0.05,"exploding":0.025}},"Discoverer":{"Main":{"lootBonus":0.99,"xpBonus":0.01}},"Crusade Sabatons":{"Main":{"rawHealth":0.85,"healthRegen":0.1,"walkSpeed":0.05}},"Resurgence":{"Main":{"manaRegen":0.4,"spellDamage":0.35,"healthRegenRaw":0.15,"walkSpeed":0.1},"Utility":{"manaRegen":0.45,"healthRegenRaw":0.3,"spellDamage":0.2,"walkSpeed":0.05}},"Galleon":{"Main":{"manaSteal":0.33,"earthDamage":0.325,"waterDamage":0.32,"rawMaxMana":0.025},"Melee":{"mainAttackDamage":0.35,"earthDamage":0.325,"manaSteal":0.3,"rawMaxMana":0.025}},"Boreal":{"Main":{"healthRegen":0.5,"healthRegenRaw":0.33,"manaRegen":0.1,"walkSpeed":0.05,"thunderDamage":0.01,"earthDamage":0.01}},"Slayer":{"Main":{"3rdSpellCost":0.475,"walkSpeed":0.25,"healthRegenRaw":0.2,"rawMainAttackDamage":0.05,"stealing":0.025},"Melee":{"rawMainAttackDamage":0.375,"walkSpeed":0.25,"healthRegenRaw":0.2,"3rdSpellCost":0.15,"stealing":0.025}},"Moontower":{"Main":{"walkSpeed":0.95,"airDefence":0.025,"waterDefence":0.025}},"Dawnbreak":{"Main":{"rawMainAttackDamage":0.55,"manaSteal":0.125,"thunderDamage":0.125,"fireDamage":0.1,"lifeSteal":0.075,"exploding":0.025},"Spell":{"fireDamage":0.275,"thunderDamage":0.275,"manaSteal":0.225,"lifeSteal":0.2,"rawMainAttackDamage":0.025}},"Stardew":{"Main":{"rawSpellDamage":0.3,"waterDamage":0.25,"manaRegen":0.25,"thunderDamage":0.2},"Spellsteal":{"rawSpellDamage":0.3,"manaSteal":0.25,"waterDamage":0.18,"thunderDamage":0.16,"manaRegen":0.11}},"Warchief":{"Main":{"mainAttackDamage":0.38,"thunderDamage":0.3,"rawMainAttackDamage":0.17,"walkSpeed":0.1,"exploding":0.05},"Earth":{"mainAttackDamage":0.35,"earthDamage":0.325,"rawMainAttackDamage":0.175,"walkSpeed":0.1,"exploding":0.05},"Spell":{"thunderDamage":0.525,"earthDamage":0.425,"walkSpeed":0.05}},"Revenant":{"Main":{"airDamage":0.425,"4thSpellCost":0.35,"walkSpeed":0.2,"earthDamage":0.025},"Earth":{"earthDamage":0.3,"walkSpeed":0.275,"4thSpellCost":0.175,"airDamage":0.1,"manaSteal":0.075,"rawHealth":0.065,"reflection":0.01},"Melee":{"rawMainAttackDamage":0.35,"walkSpeed":0.15,"rawHealth":0.15,"mainAttackDamage":0.15,"airDamage":0.125,"earthDamage":0.075}},"Bloodbath":{"Main":{"raw1stSpellCost":0.475,"walkSpeed":0.275,"rawHealth":0.2,"lifeSteal":0.05},"Bloodpact":{"raw1stSpellCost":0.5,"walkSpeed":0.3,"rawHealth":-0.15,"lifeSteal":0.05}},"Trance":{"Main":{"manaSteal":0.7,"walkSpeed":0.2,"lifeSteal":0.1},"Melee":{"manaSteal":0.4,"rawAttackSpeed":0.35,"walkSpeed":0.125,"lifeSteal":0.125}},"Labyrinth":{"Main":{"fireDamage":0.475,"earthDamage":0.4,"3rdSpellCost":0.1,"manaSteal":0.025}},"Hanafubuki":{"Main":{"elementalDamage":0.8,"3rdSpellCost":0.125,"4thSpellCost":0.05,"jumpHeight":0.025}},"Resonance":{"Main":{"elementalSpellDamage":0.8,"4thSpellCost":0.15,"manaRegen":0.05},"Hpr%":{"elementalSpellDamage":0.4,"4thSpellCost":0.225,"manaRegen":0.225,"healthRegen":0.14,"airDefence":0.01}},"Vengeance":{"Main":{"damage":0.55,"manaSteal":0.25,"healthRegenRaw":0.15,"3rdSpellCost":0.03},"Spell":{"damage":0.36,"manaSteal":0.26,"3rdSpellCost":0.26,"healthRegen":0.1,"healthRegenRaw":0.02}},"Riptide":{"Main":{"rawWaterSpellDamage":0.49,"raw3rdSpellCost":0.39,"rawMaxMana":0.2,"manaSteal":0.1}},"Revolution":{"Main":{"rawHealth":0.5,"raw2ndSpellCost":0.3,"manaSteal":0.15,"mainAttackRange":0.05}},"Ascendancy":{"Main":{"rawSpellDamage":0.4,"fireDamage":0.35,"rawHealth":0.24,"reflection":0.01}},"Transfiguration":{"Main":{"rawElementalDamage":0.7,"manaSteal":0.3}},"Restitution":{"Main":{"thunderSpellDamage":0.35,"raw3rdSpellCost":0.25,"manaRegen":0.2,"walkSpeed":0.15,"rawHealth":0.05}},"Eschaton":{"Main":{"rawHealth":0.4,"rawFireDamage":0.4,"exploding":0.15,"4thSpellCost":0.05}},"Halcyon":{"Main":{"rawHealth":0.28,"rawElementalSpellDamage":0.25,"healingEfficiency":0.22,"raw4thSpellCost":0.2,"elementalDefence":0.03,"reflection":0.02}},"Architect":{"Main":{"healingEfficiency":0.4,"manaRegen":0.2,"rawHealth":0.2,"lifeSteal":0.15,"slowEnemy":0.05}},"Fate":{"Main":{"rawElementalMainAttackDamage":0.4,"raw4thSpellCost":0.2,"weakenEnemy":0.2,"walkSpeed":0.15,"3rdSpellCost":0.05}}}}